plexflo/__init__.py
plexflo/connect/__init__.py
plexflo/connect/listen.py
plexflo/connect/stream.py
plexflo/datastream/__init__.py
plexflo/datastream/finetune.py
plexflo/datastream/inference.py
plexflo/datastream/model.py
plexflo/datastream/utils.py
plexflo/datastream/models/model_15min.h5
plexflo/loadprofiles/__init__.py
plexflo/loadprofiles/profiles.py
plexflo/loadprofiles/files/.DS_Store
plexflo/loadprofiles/files/afternoon_peak_average_household_WD_SH.csv
plexflo/loadprofiles/files/afternoon_peak_average_household_WD_SU.csv
plexflo/loadprofiles/files/afternoon_peak_average_household_WD_WI.csv
plexflo/loadprofiles/files/afternoon_peak_average_household_WE_SH.csv
plexflo/loadprofiles/files/afternoon_peak_average_household_WE_SU.csv
plexflo/loadprofiles/files/afternoon_peak_average_household_WE_WI.csv
plexflo/loadprofiles/files/dual_peak_average_household_WD_SH.csv
plexflo/loadprofiles/files/dual_peak_average_household_WD_SU.csv
plexflo/loadprofiles/files/dual_peak_average_household_WD_WI.csv
plexflo/loadprofiles/files/dual_peak_average_household_WE_SH.csv
plexflo/loadprofiles/files/dual_peak_average_household_WE_SU.csv
plexflo/loadprofiles/files/dual_peak_average_household_WE_WI.csv
plexflo/loadprofiles/files/evening_peak_average_household_WD_SH.csv
plexflo/loadprofiles/files/evening_peak_average_household_WD_SU.csv
plexflo/loadprofiles/files/evening_peak_average_household_WD_WI.csv
plexflo/loadprofiles/files/evening_peak_average_household_WE_SH.csv
plexflo/loadprofiles/files/evening_peak_average_household_WE_SU.csv
plexflo/loadprofiles/files/evening_peak_average_household_WE_WI.csv
plexflo/loadprofiles/files/morning_peak_average_household_WD_SH.csv
plexflo/loadprofiles/files/morning_peak_average_household_WD_SU.csv
plexflo/loadprofiles/files/morning_peak_average_household_WD_WI.csv
plexflo/loadprofiles/files/morning_peak_average_household_WE_SH.csv
plexflo/loadprofiles/files/morning_peak_average_household_WE_SU.csv
plexflo-1.2.1.dist-info/LICENSE
plexflo-1.2.1.dist-info/METADATA
plexflo-1.2.1.dist-info/WHEEL
plexflo-1.2.1.dist-info/top_level.txt
plexflo-1.2.1.dist-info/RECORD
