Metadata-Version: 2.1
Name: plexflo
Version: 1.2.1
Summary: Open-source Python wrapper around Plexflo's apps, APIs, and algorithms that help researchers, engineers and energy companies build intelligence, apps, and dashboards to accelerate clean-tech adoption across all communities.
Home-page: https://github.com/plexflo/plexflo
Author: Plexflo
Author-email: hello@plexflo.com
Classifier: Programming Language :: Python :: 3
Classifier: License :: OSI Approved :: MIT License
Classifier: Operating System :: OS Independent
Requires-Python: >=3.6
License-File: LICENSE
Requires-Dist: numpy
Requires-Dist: pandas
Requires-Dist: sklearn
Requires-Dist: openpyxl
Requires-Dist: pathlib
Requires-Dist: matplotlib
Requires-Dist: scipy
Requires-Dist: fitter
